mycelium_forest/__init__.py
mycelium_forest/mycelium_forest.py
mycelium_forest-1.0.0.dist-info/METADATA
mycelium_forest-1.0.0.dist-info/WHEEL
mycelium_forest-1.0.0.dist-info/top_level.txt
mycelium_forest-1.0.0.dist-info/RECORD
