Metadata-Version: 2.4
Name: mycelium_forest
Version: 1.0.0
Summary: Visualize Random Forest trees with mycelium-inspired network representations
Author: Derya Kapisiz
Author-email: dkapisiz.data@gmail.com
Classifier: Programming Language :: Python :: 3
Classifier: License :: OSI Approved :: MIT License
Classifier: Operating System :: OS Independent
Requires-Python: >=3.7
Requires-Dist: numpy>=1.19.0
Requires-Dist: pandas>=1.3.0
Requires-Dist: scikit-learn>=1.0.0
Requires-Dist: matplotlib>=3.3.0
Requires-Dist: scipy>=1.7.0
Dynamic: author
Dynamic: author-email
Dynamic: classifier
Dynamic: requires-dist
Dynamic: requires-python
Dynamic: summary
